LICENSE.txt
LocalResolver.py
MANIFEST.in
README.md
setup.cfg
setup.py
LocalResolver.egg-info/PKG-INFO
LocalResolver.egg-info/SOURCES.txt
LocalResolver.egg-info/dependency_links.txt
LocalResolver.egg-info/entry_points.txt
LocalResolver.egg-info/requires.txt
LocalResolver.egg-info/top_level.txt