Metadata-Version: 2.1
Name: LocalResolver
Version: 1.0.1
Summary: This package implements local hostname resolver tool with scapy.
Home-page: https://github.com/mauricelambert/LocalResolver
Author: Maurice Lambert
Author-email: mauricelambert434@gmail.com
Maintainer: Maurice Lambert
Maintainer-email: mauricelambert434@gmail.com
License: GPL-3.0 License
Project-URL: Executable, https://mauricelambert.github.io/info/python/code/LocalResolver.pyz
Project-URL: Documentation, https://mauricelambert.github.io/info/python/code/LocalResolver.html
Keywords: Resolve,Hostname,LLMNR,Netbios
Platform: Windows
Platform: Linux
Platform: MacOS
Classifier: Environment :: Console
Classifier: Natural Language :: English
Classifier: Programming Language :: Python
Classifier: Programming Language :: Python :: 3.9
Classifier: Operating System :: MacOS
Classifier: Operating System :: POSIX :: Linux
Classifier: Operating System :: Microsoft :: Windows
Classifier: Development Status :: 5 - Production/Stable
Classifier: License :: OSI Approved :: GNU General Public License v3 (GPLv3)
Requires-Python: >=3.8
License-File: LICENSE.txt
